<?xml version="1.0" encoding="UTF-8"?><record_update>
    <sys_ui_section action="DELETE" caption="Disease Surveillance" section_id="17d0c8b1dbaa17009b2689584b96197e" sys_domain="global" table="x_cria_livestock_t_vaccinations_cvi" version="3" view="">
        <sys_ui_element action="INSERT_OR_UPDATE">
            <element>cvi_brucellosis</element>
            <position>0</position>
            <sys_created_by>cervin@criadvantage.com</sys_created_by>
            <sys_created_on>2018-06-07 16:42:59</sys_created_on>
            <sys_id>bd609c7ddbaa17009b2689584b96194f</sys_id>
            <sys_mod_count>0</sys_mod_count>
            <sys_ui_formatter/>
            <sys_ui_section caption="Disease Surveillance" display_value="Disease Surveillance" name="x_cria_livestock_t_vaccinations_cvi" sys_domain="global" view="Default view">17d0c8b1dbaa17009b2689584b96197e</sys_ui_section>
            <sys_updated_by>cervin@criadvantage.com</sys_updated_by>
            <sys_updated_on>2018-06-07 16:42:59</sys_updated_on>
            <sys_user/>
            <type/>
        </sys_ui_element>
        <sys_ui_element action="INSERT_OR_UPDATE">
            <element>.split</element>
            <position>1</position>
            <sys_created_by>cervin@criadvantage.com</sys_created_by>
            <sys_created_on>2018-06-07 16:42:59</sys_created_on>
            <sys_id>35609c7ddbaa17009b2689584b961950</sys_id>
            <sys_mod_count>0</sys_mod_count>
            <sys_ui_formatter/>
            <sys_ui_section caption="Disease Surveillance" display_value="Disease Surveillance" name="x_cria_livestock_t_vaccinations_cvi" sys_domain="global" view="Default view">17d0c8b1dbaa17009b2689584b96197e</sys_ui_section>
            <sys_updated_by>cervin@criadvantage.com</sys_updated_by>
            <sys_updated_on>2018-06-07 16:42:59</sys_updated_on>
            <sys_user/>
            <type>.split</type>
        </sys_ui_element>
        <sys_ui_element action="INSERT_OR_UPDATE">
            <element>laboratory</element>
            <position>2</position>
            <sys_created_by>cervin@criadvantage.com</sys_created_by>
            <sys_created_on>2018-06-07 16:42:59</sys_created_on>
            <sys_id>b5609c7ddbaa17009b2689584b961950</sys_id>
            <sys_mod_count>0</sys_mod_count>
            <sys_ui_formatter/>
            <sys_ui_section caption="Disease Surveillance" display_value="Disease Surveillance" name="x_cria_livestock_t_vaccinations_cvi" sys_domain="global" view="Default view">17d0c8b1dbaa17009b2689584b96197e</sys_ui_section>
            <sys_updated_by>cervin@criadvantage.com</sys_updated_by>
            <sys_updated_on>2018-06-07 16:42:59</sys_updated_on>
            <sys_user/>
            <type/>
        </sys_ui_element>
        <sys_ui_element action="INSERT_OR_UPDATE">
            <element>date_bled</element>
            <position>3</position>
            <sys_created_by>cervin@criadvantage.com</sys_created_by>
            <sys_created_on>2018-06-07 16:42:59</sys_created_on>
            <sys_id>39609c7ddbaa17009b2689584b961950</sys_id>
            <sys_mod_count>0</sys_mod_count>
            <sys_ui_formatter/>
            <sys_ui_section caption="Disease Surveillance" display_value="Disease Surveillance" name="x_cria_livestock_t_vaccinations_cvi" sys_domain="global" view="Default view">17d0c8b1dbaa17009b2689584b96197e</sys_ui_section>
            <sys_updated_by>cervin@criadvantage.com</sys_updated_by>
            <sys_updated_on>2018-06-07 16:42:59</sys_updated_on>
            <sys_user/>
            <type/>
        </sys_ui_element>
        <sys_ui_element action="INSERT_OR_UPDATE">
            <element>number_of_test_eligible_cattle</element>
            <position>4</position>
            <sys_created_by>cervin@criadvantage.com</sys_created_by>
            <sys_created_on>2018-06-07 16:42:59</sys_created_on>
            <sys_id>b9609c7ddbaa17009b2689584b961950</sys_id>
            <sys_mod_count>0</sys_mod_count>
            <sys_ui_formatter/>
            <sys_ui_section caption="Disease Surveillance" display_value="Disease Surveillance" name="x_cria_livestock_t_vaccinations_cvi" sys_domain="global" view="Default view">17d0c8b1dbaa17009b2689584b96197e</sys_ui_section>
            <sys_updated_by>cervin@criadvantage.com</sys_updated_by>
            <sys_updated_on>2018-06-07 16:42:59</sys_updated_on>
            <sys_user/>
            <type/>
        </sys_ui_element>
        <sys_ui_element action="INSERT_OR_UPDATE">
            <element>number_of_brucellosis_negative_cattle</element>
            <position>5</position>
            <sys_created_by>cervin@criadvantage.com</sys_created_by>
            <sys_created_on>2018-06-07 16:42:59</sys_created_on>
            <sys_id>3d609c7ddbaa17009b2689584b961950</sys_id>
            <sys_mod_count>0</sys_mod_count>
            <sys_ui_formatter/>
            <sys_ui_section caption="Disease Surveillance" display_value="Disease Surveillance" name="x_cria_livestock_t_vaccinations_cvi" sys_domain="global" view="Default view">17d0c8b1dbaa17009b2689584b96197e</sys_ui_section>
            <sys_updated_by>cervin@criadvantage.com</sys_updated_by>
            <sys_updated_on>2018-06-07 16:42:59</sys_updated_on>
            <sys_user/>
            <type/>
        </sys_ui_element>
        <sys_ui_element action="INSERT_OR_UPDATE">
            <element>.end_split</element>
            <position>6</position>
            <sys_created_by>cervin@criadvantage.com</sys_created_by>
            <sys_created_on>2018-06-07 16:42:59</sys_created_on>
            <sys_id>bd609c7ddbaa17009b2689584b961950</sys_id>
            <sys_mod_count>0</sys_mod_count>
            <sys_ui_formatter/>
            <sys_ui_section caption="Disease Surveillance" display_value="Disease Surveillance" name="x_cria_livestock_t_vaccinations_cvi" sys_domain="global" view="Default view">17d0c8b1dbaa17009b2689584b96197e</sys_ui_section>
            <sys_updated_by>cervin@criadvantage.com</sys_updated_by>
            <sys_updated_on>2018-06-07 16:42:59</sys_updated_on>
            <sys_user/>
            <type>.end_split</type>
        </sys_ui_element>
        <sys_ui_element action="INSERT_OR_UPDATE">
            <element>.begin_split</element>
            <position>7</position>
            <sys_created_by>cervin@criadvantage.com</sys_created_by>
            <sys_created_on>2018-06-07 16:42:59</sys_created_on>
            <sys_id>31609c7ddbaa17009b2689584b961951</sys_id>
            <sys_mod_count>0</sys_mod_count>
            <sys_ui_formatter/>
            <sys_ui_section caption="Disease Surveillance" display_value="Disease Surveillance" name="x_cria_livestock_t_vaccinations_cvi" sys_domain="global" view="Default view">17d0c8b1dbaa17009b2689584b96197e</sys_ui_section>
            <sys_updated_by>cervin@criadvantage.com</sys_updated_by>
            <sys_updated_on>2018-06-07 16:42:59</sys_updated_on>
            <sys_user/>
            <type>.begin_split</type>
        </sys_ui_element>
        <sys_ui_element action="INSERT_OR_UPDATE">
            <element>cvi_trichomonisis</element>
            <position>8</position>
            <sys_created_by>cervin@criadvantage.com</sys_created_by>
            <sys_created_on>2018-06-07 16:42:59</sys_created_on>
            <sys_id>b1609c7ddbaa17009b2689584b961951</sys_id>
            <sys_mod_count>0</sys_mod_count>
            <sys_ui_formatter/>
            <sys_ui_section caption="Disease Surveillance" display_value="Disease Surveillance" name="x_cria_livestock_t_vaccinations_cvi" sys_domain="global" view="Default view">17d0c8b1dbaa17009b2689584b96197e</sys_ui_section>
            <sys_updated_by>cervin@criadvantage.com</sys_updated_by>
            <sys_updated_on>2018-06-07 16:42:59</sys_updated_on>
            <sys_user/>
            <type/>
        </sys_ui_element>
        <sys_ui_element action="INSERT_OR_UPDATE">
            <element>.split</element>
            <position>9</position>
            <sys_created_by>cervin@criadvantage.com</sys_created_by>
            <sys_created_on>2018-06-07 16:42:59</sys_created_on>
            <sys_id>35609c7ddbaa17009b2689584b961951</sys_id>
            <sys_mod_count>0</sys_mod_count>
            <sys_ui_formatter/>
            <sys_ui_section caption="Disease Surveillance" display_value="Disease Surveillance" name="x_cria_livestock_t_vaccinations_cvi" sys_domain="global" view="Default view">17d0c8b1dbaa17009b2689584b96197e</sys_ui_section>
            <sys_updated_by>cervin@criadvantage.com</sys_updated_by>
            <sys_updated_on>2018-06-07 16:42:59</sys_updated_on>
            <sys_user/>
            <type>.split</type>
        </sys_ui_element>
        <sys_ui_element action="INSERT_OR_UPDATE">
            <element>trich_laboratory</element>
            <position>10</position>
            <sys_created_by>cervin@criadvantage.com</sys_created_by>
            <sys_created_on>2018-06-07 16:42:59</sys_created_on>
            <sys_id>b5609c7ddbaa17009b2689584b961951</sys_id>
            <sys_mod_count>0</sys_mod_count>
            <sys_ui_formatter/>
            <sys_ui_section caption="Disease Surveillance" display_value="Disease Surveillance" name="x_cria_livestock_t_vaccinations_cvi" sys_domain="global" view="Default view">17d0c8b1dbaa17009b2689584b96197e</sys_ui_section>
            <sys_updated_by>cervin@criadvantage.com</sys_updated_by>
            <sys_updated_on>2018-06-07 16:42:59</sys_updated_on>
            <sys_user/>
            <type/>
        </sys_ui_element>
        <sys_ui_element action="INSERT_OR_UPDATE">
            <element>date_sample_collected</element>
            <position>11</position>
            <sys_created_by>cervin@criadvantage.com</sys_created_by>
            <sys_created_on>2018-06-07 16:42:59</sys_created_on>
            <sys_id>39609c7ddbaa17009b2689584b961951</sys_id>
            <sys_mod_count>0</sys_mod_count>
            <sys_ui_formatter/>
            <sys_ui_section caption="Disease Surveillance" display_value="Disease Surveillance" name="x_cria_livestock_t_vaccinations_cvi" sys_domain="global" view="Default view">17d0c8b1dbaa17009b2689584b96197e</sys_ui_section>
            <sys_updated_by>cervin@criadvantage.com</sys_updated_by>
            <sys_updated_on>2018-06-07 16:42:59</sys_updated_on>
            <sys_user/>
            <type/>
        </sys_ui_element>
        <sys_ui_element action="INSERT_OR_UPDATE">
            <element>accession_num</element>
            <position>12</position>
            <sys_created_by>cervin@criadvantage.com</sys_created_by>
            <sys_created_on>2018-06-07 16:42:59</sys_created_on>
            <sys_id>b9609c7ddbaa17009b2689584b961951</sys_id>
            <sys_mod_count>0</sys_mod_count>
            <sys_ui_formatter/>
            <sys_ui_section caption="Disease Surveillance" display_value="Disease Surveillance" name="x_cria_livestock_t_vaccinations_cvi" sys_domain="global" view="Default view">17d0c8b1dbaa17009b2689584b96197e</sys_ui_section>
            <sys_updated_by>cervin@criadvantage.com</sys_updated_by>
            <sys_updated_on>2018-06-07 16:42:59</sys_updated_on>
            <sys_user/>
            <type/>
        </sys_ui_element>
        <sys_ui_element action="INSERT_OR_UPDATE">
            <element>all_eligible_bulls_neg</element>
            <position>13</position>
            <sys_created_by>cervin@criadvantage.com</sys_created_by>
            <sys_created_on>2018-06-07 16:42:59</sys_created_on>
            <sys_id>3d609c7ddbaa17009b2689584b961951</sys_id>
            <sys_mod_count>0</sys_mod_count>
            <sys_ui_formatter/>
            <sys_ui_section caption="Disease Surveillance" display_value="Disease Surveillance" name="x_cria_livestock_t_vaccinations_cvi" sys_domain="global" view="Default view">17d0c8b1dbaa17009b2689584b96197e</sys_ui_section>
            <sys_updated_by>cervin@criadvantage.com</sys_updated_by>
            <sys_updated_on>2018-06-07 16:42:59</sys_updated_on>
            <sys_user/>
            <type/>
        </sys_ui_element>
        <sys_ui_element action="INSERT_OR_UPDATE">
            <element>.end_split</element>
            <position>14</position>
            <sys_created_by>cervin@criadvantage.com</sys_created_by>
            <sys_created_on>2018-06-07 16:42:59</sys_created_on>
            <sys_id>bd609c7ddbaa17009b2689584b961951</sys_id>
            <sys_mod_count>0</sys_mod_count>
            <sys_ui_formatter/>
            <sys_ui_section caption="Disease Surveillance" display_value="Disease Surveillance" name="x_cria_livestock_t_vaccinations_cvi" sys_domain="global" view="Default view">17d0c8b1dbaa17009b2689584b96197e</sys_ui_section>
            <sys_updated_by>cervin@criadvantage.com</sys_updated_by>
            <sys_updated_on>2018-06-07 16:42:59</sys_updated_on>
            <sys_user/>
            <type>.end_split</type>
        </sys_ui_element>
        <sys_ui_element action="INSERT_OR_UPDATE">
            <element>.begin_split</element>
            <position>15</position>
            <sys_created_by>cervin@criadvantage.com</sys_created_by>
            <sys_created_on>2018-06-07 16:42:59</sys_created_on>
            <sys_id>31609c7ddbaa17009b2689584b961952</sys_id>
            <sys_mod_count>0</sys_mod_count>
            <sys_ui_formatter/>
            <sys_ui_section caption="Disease Surveillance" display_value="Disease Surveillance" name="x_cria_livestock_t_vaccinations_cvi" sys_domain="global" view="Default view">17d0c8b1dbaa17009b2689584b96197e</sys_ui_section>
            <sys_updated_by>cervin@criadvantage.com</sys_updated_by>
            <sys_updated_on>2018-06-07 16:42:59</sys_updated_on>
            <sys_user/>
            <type>.begin_split</type>
        </sys_ui_element>
        <sys_ui_element action="INSERT_OR_UPDATE">
            <element>cvi_tuberculosis</element>
            <position>16</position>
            <sys_created_by>cervin@criadvantage.com</sys_created_by>
            <sys_created_on>2018-06-07 16:42:59</sys_created_on>
            <sys_id>b1609c7ddbaa17009b2689584b961952</sys_id>
            <sys_mod_count>0</sys_mod_count>
            <sys_ui_formatter/>
            <sys_ui_section caption="Disease Surveillance" display_value="Disease Surveillance" name="x_cria_livestock_t_vaccinations_cvi" sys_domain="global" view="Default view">17d0c8b1dbaa17009b2689584b96197e</sys_ui_section>
            <sys_updated_by>cervin@criadvantage.com</sys_updated_by>
            <sys_updated_on>2018-06-07 16:42:59</sys_updated_on>
            <sys_user/>
            <type/>
        </sys_ui_element>
        <sys_ui_element action="INSERT_OR_UPDATE">
            <element>.split</element>
            <position>17</position>
            <sys_created_by>cervin@criadvantage.com</sys_created_by>
            <sys_created_on>2018-06-07 16:42:59</sys_created_on>
            <sys_id>35609c7ddbaa17009b2689584b961952</sys_id>
            <sys_mod_count>0</sys_mod_count>
            <sys_ui_formatter/>
            <sys_ui_section caption="Disease Surveillance" display_value="Disease Surveillance" name="x_cria_livestock_t_vaccinations_cvi" sys_domain="global" view="Default view">17d0c8b1dbaa17009b2689584b96197e</sys_ui_section>
            <sys_updated_by>cervin@criadvantage.com</sys_updated_by>
            <sys_updated_on>2018-06-07 16:42:59</sys_updated_on>
            <sys_user/>
            <type>.split</type>
        </sys_ui_element>
        <sys_ui_element action="INSERT_OR_UPDATE">
            <element>all_animals_neg</element>
            <position>18</position>
            <sys_created_by>cervin@criadvantage.com</sys_created_by>
            <sys_created_on>2018-06-07 16:42:59</sys_created_on>
            <sys_id>b5609c7ddbaa17009b2689584b961952</sys_id>
            <sys_mod_count>0</sys_mod_count>
            <sys_ui_formatter/>
            <sys_ui_section caption="Disease Surveillance" display_value="Disease Surveillance" name="x_cria_livestock_t_vaccinations_cvi" sys_domain="global" view="Default view">17d0c8b1dbaa17009b2689584b96197e</sys_ui_section>
            <sys_updated_by>cervin@criadvantage.com</sys_updated_by>
            <sys_updated_on>2018-06-07 16:42:59</sys_updated_on>
            <sys_user/>
            <type/>
        </sys_ui_element>
        <sys_ui_element action="INSERT_OR_UPDATE">
            <element>tub_date</element>
            <position>19</position>
            <sys_created_by>cervin@criadvantage.com</sys_created_by>
            <sys_created_on>2018-06-07 16:42:59</sys_created_on>
            <sys_id>39609c7ddbaa17009b2689584b961952</sys_id>
            <sys_mod_count>0</sys_mod_count>
            <sys_ui_formatter/>
            <sys_ui_section caption="Disease Surveillance" display_value="Disease Surveillance" name="x_cria_livestock_t_vaccinations_cvi" sys_domain="global" view="Default view">17d0c8b1dbaa17009b2689584b96197e</sys_ui_section>
            <sys_updated_by>cervin@criadvantage.com</sys_updated_by>
            <sys_updated_on>2018-06-07 16:42:59</sys_updated_on>
            <sys_user/>
            <type/>
        </sys_ui_element>
        <sys_ui_element action="INSERT_OR_UPDATE">
            <element>.end_split</element>
            <position>20</position>
            <sys_created_by>cervin@criadvantage.com</sys_created_by>
            <sys_created_on>2018-06-07 16:42:59</sys_created_on>
            <sys_id>b9609c7ddbaa17009b2689584b961952</sys_id>
            <sys_mod_count>0</sys_mod_count>
            <sys_ui_formatter/>
            <sys_ui_section caption="Disease Surveillance" display_value="Disease Surveillance" name="x_cria_livestock_t_vaccinations_cvi" sys_domain="global" view="Default view">17d0c8b1dbaa17009b2689584b96197e</sys_ui_section>
            <sys_updated_by>cervin@criadvantage.com</sys_updated_by>
            <sys_updated_on>2018-06-07 16:42:59</sys_updated_on>
            <sys_user/>
            <type>.end_split</type>
        </sys_ui_element>
        <sys_ui_element action="INSERT_OR_UPDATE">
            <element>.begin_split</element>
            <position>21</position>
            <sys_created_by>cervin@criadvantage.com</sys_created_by>
            <sys_created_on>2018-06-07 16:42:59</sys_created_on>
            <sys_id>3d609c7ddbaa17009b2689584b961952</sys_id>
            <sys_mod_count>0</sys_mod_count>
            <sys_ui_formatter/>
            <sys_ui_section caption="Disease Surveillance" display_value="Disease Surveillance" name="x_cria_livestock_t_vaccinations_cvi" sys_domain="global" view="Default view">17d0c8b1dbaa17009b2689584b96197e</sys_ui_section>
            <sys_updated_by>cervin@criadvantage.com</sys_updated_by>
            <sys_updated_on>2018-06-07 16:42:59</sys_updated_on>
            <sys_user/>
            <type>.begin_split</type>
        </sys_ui_element>
        <sys_ui_element action="INSERT_OR_UPDATE">
            <element>cvi_equine_infectious_anemia</element>
            <position>22</position>
            <sys_created_by>cervin@criadvantage.com</sys_created_by>
            <sys_created_on>2018-06-07 16:42:59</sys_created_on>
            <sys_id>bd609c7ddbaa17009b2689584b961952</sys_id>
            <sys_mod_count>0</sys_mod_count>
            <sys_ui_formatter/>
            <sys_ui_section caption="Disease Surveillance" display_value="Disease Surveillance" name="x_cria_livestock_t_vaccinations_cvi" sys_domain="global" view="Default view">17d0c8b1dbaa17009b2689584b96197e</sys_ui_section>
            <sys_updated_by>cervin@criadvantage.com</sys_updated_by>
            <sys_updated_on>2018-06-07 16:42:59</sys_updated_on>
            <sys_user/>
            <type/>
        </sys_ui_element>
        <sys_ui_element action="INSERT_OR_UPDATE">
            <element>.split</element>
            <position>23</position>
            <sys_created_by>cervin@criadvantage.com</sys_created_by>
            <sys_created_on>2018-06-07 16:42:59</sys_created_on>
            <sys_id>31609c7ddbaa17009b2689584b961953</sys_id>
            <sys_mod_count>0</sys_mod_count>
            <sys_ui_formatter/>
            <sys_ui_section caption="Disease Surveillance" display_value="Disease Surveillance" name="x_cria_livestock_t_vaccinations_cvi" sys_domain="global" view="Default view">17d0c8b1dbaa17009b2689584b96197e</sys_ui_section>
            <sys_updated_by>cervin@criadvantage.com</sys_updated_by>
            <sys_updated_on>2018-06-07 16:42:59</sys_updated_on>
            <sys_user/>
            <type>.split</type>
        </sys_ui_element>
        <sys_ui_element action="INSERT_OR_UPDATE">
            <element>eia_laboratory</element>
            <position>24</position>
            <sys_created_by>cervin@criadvantage.com</sys_created_by>
            <sys_created_on>2018-06-07 16:42:59</sys_created_on>
            <sys_id>b1609c7ddbaa17009b2689584b961953</sys_id>
            <sys_mod_count>0</sys_mod_count>
            <sys_ui_formatter/>
            <sys_ui_section caption="Disease Surveillance" display_value="Disease Surveillance" name="x_cria_livestock_t_vaccinations_cvi" sys_domain="global" view="Default view">17d0c8b1dbaa17009b2689584b96197e</sys_ui_section>
            <sys_updated_by>cervin@criadvantage.com</sys_updated_by>
            <sys_updated_on>2018-06-07 16:42:59</sys_updated_on>
            <sys_user/>
            <type/>
        </sys_ui_element>
        <sys_ui_element action="INSERT_OR_UPDATE">
            <element>eia_accession</element>
            <position>25</position>
            <sys_created_by>cervin@criadvantage.com</sys_created_by>
            <sys_created_on>2018-06-07 16:42:59</sys_created_on>
            <sys_id>35609c7ddbaa17009b2689584b961953</sys_id>
            <sys_mod_count>0</sys_mod_count>
            <sys_ui_formatter/>
            <sys_ui_section caption="Disease Surveillance" display_value="Disease Surveillance" name="x_cria_livestock_t_vaccinations_cvi" sys_domain="global" view="Default view">17d0c8b1dbaa17009b2689584b96197e</sys_ui_section>
            <sys_updated_by>cervin@criadvantage.com</sys_updated_by>
            <sys_updated_on>2018-06-07 16:42:59</sys_updated_on>
            <sys_user/>
            <type/>
        </sys_ui_element>
        <sys_ui_element action="INSERT_OR_UPDATE">
            <element>date_of_coggins</element>
            <position>26</position>
            <sys_created_by>cervin@criadvantage.com</sys_created_by>
            <sys_created_on>2018-06-07 16:42:59</sys_created_on>
            <sys_id>b5609c7ddbaa17009b2689584b961953</sys_id>
            <sys_mod_count>0</sys_mod_count>
            <sys_ui_formatter/>
            <sys_ui_section caption="Disease Surveillance" display_value="Disease Surveillance" name="x_cria_livestock_t_vaccinations_cvi" sys_domain="global" view="Default view">17d0c8b1dbaa17009b2689584b96197e</sys_ui_section>
            <sys_updated_by>cervin@criadvantage.com</sys_updated_by>
            <sys_updated_on>2018-06-07 16:42:59</sys_updated_on>
            <sys_user/>
            <type/>
        </sys_ui_element>
        <sys_ui_element action="INSERT_OR_UPDATE">
            <element>.end_split</element>
            <position>27</position>
            <sys_created_by>cervin@criadvantage.com</sys_created_by>
            <sys_created_on>2018-06-07 16:42:59</sys_created_on>
            <sys_id>39609c7ddbaa17009b2689584b961953</sys_id>
            <sys_mod_count>0</sys_mod_count>
            <sys_ui_formatter/>
            <sys_ui_section caption="Disease Surveillance" display_value="Disease Surveillance" name="x_cria_livestock_t_vaccinations_cvi" sys_domain="global" view="Default view">17d0c8b1dbaa17009b2689584b96197e</sys_ui_section>
            <sys_updated_by>cervin@criadvantage.com</sys_updated_by>
            <sys_updated_on>2018-06-07 16:42:59</sys_updated_on>
            <sys_user/>
            <type>.end_split</type>
        </sys_ui_element>
        <sys_ui_element action="INSERT_OR_UPDATE">
            <element>.begin_split</element>
            <position>28</position>
            <sys_created_by>cervin@criadvantage.com</sys_created_by>
            <sys_created_on>2018-06-07 16:42:59</sys_created_on>
            <sys_id>b9609c7ddbaa17009b2689584b961953</sys_id>
            <sys_mod_count>0</sys_mod_count>
            <sys_ui_formatter/>
            <sys_ui_section caption="Disease Surveillance" display_value="Disease Surveillance" name="x_cria_livestock_t_vaccinations_cvi" sys_domain="global" view="Default view">17d0c8b1dbaa17009b2689584b96197e</sys_ui_section>
            <sys_updated_by>cervin@criadvantage.com</sys_updated_by>
            <sys_updated_on>2018-06-07 16:42:59</sys_updated_on>
            <sys_user/>
            <type>.begin_split</type>
        </sys_ui_element>
        <sys_ui_element action="INSERT_OR_UPDATE">
            <element>cvi_other</element>
            <position>29</position>
            <sys_created_by>cervin@criadvantage.com</sys_created_by>
            <sys_created_on>2018-06-07 16:42:59</sys_created_on>
            <sys_id>3d609c7ddbaa17009b2689584b961953</sys_id>
            <sys_mod_count>0</sys_mod_count>
            <sys_ui_formatter/>
            <sys_ui_section caption="Disease Surveillance" display_value="Disease Surveillance" name="x_cria_livestock_t_vaccinations_cvi" sys_domain="global" view="Default view">17d0c8b1dbaa17009b2689584b96197e</sys_ui_section>
            <sys_updated_by>cervin@criadvantage.com</sys_updated_by>
            <sys_updated_on>2018-06-07 16:42:59</sys_updated_on>
            <sys_user/>
            <type/>
        </sys_ui_element>
        <sys_ui_element action="INSERT_OR_UPDATE">
            <element>.split</element>
            <position>30</position>
            <sys_created_by>cervin@criadvantage.com</sys_created_by>
            <sys_created_on>2018-06-07 16:42:59</sys_created_on>
            <sys_id>bd609c7ddbaa17009b2689584b961953</sys_id>
            <sys_mod_count>0</sys_mod_count>
            <sys_ui_formatter/>
            <sys_ui_section caption="Disease Surveillance" display_value="Disease Surveillance" name="x_cria_livestock_t_vaccinations_cvi" sys_domain="global" view="Default view">17d0c8b1dbaa17009b2689584b96197e</sys_ui_section>
            <sys_updated_by>cervin@criadvantage.com</sys_updated_by>
            <sys_updated_on>2018-06-07 16:42:59</sys_updated_on>
            <sys_user/>
            <type>.split</type>
        </sys_ui_element>
        <sys_ui_element action="INSERT_OR_UPDATE">
            <element>other_test</element>
            <position>31</position>
            <sys_created_by>cervin@criadvantage.com</sys_created_by>
            <sys_created_on>2018-06-07 16:42:59</sys_created_on>
            <sys_id>31609c7ddbaa17009b2689584b961954</sys_id>
            <sys_mod_count>0</sys_mod_count>
            <sys_ui_formatter/>
            <sys_ui_section caption="Disease Surveillance" display_value="Disease Surveillance" name="x_cria_livestock_t_vaccinations_cvi" sys_domain="global" view="Default view">17d0c8b1dbaa17009b2689584b96197e</sys_ui_section>
            <sys_updated_by>cervin@criadvantage.com</sys_updated_by>
            <sys_updated_on>2018-06-07 16:42:59</sys_updated_on>
            <sys_user/>
            <type/>
        </sys_ui_element>
        <sys_ui_element action="INSERT_OR_UPDATE">
            <element>other_results</element>
            <position>32</position>
            <sys_created_by>cervin@criadvantage.com</sys_created_by>
            <sys_created_on>2018-06-07 16:42:59</sys_created_on>
            <sys_id>b1609c7ddbaa17009b2689584b961954</sys_id>
            <sys_mod_count>0</sys_mod_count>
            <sys_ui_formatter/>
            <sys_ui_section caption="Disease Surveillance" display_value="Disease Surveillance" name="x_cria_livestock_t_vaccinations_cvi" sys_domain="global" view="Default view">17d0c8b1dbaa17009b2689584b96197e</sys_ui_section>
            <sys_updated_by>cervin@criadvantage.com</sys_updated_by>
            <sys_updated_on>2018-06-07 16:42:59</sys_updated_on>
            <sys_user/>
            <type/>
        </sys_ui_element>
        <sys_ui_element action="INSERT_OR_UPDATE">
            <element>other_lab</element>
            <position>33</position>
            <sys_created_by>cervin@criadvantage.com</sys_created_by>
            <sys_created_on>2018-06-07 16:42:59</sys_created_on>
            <sys_id>35609c7ddbaa17009b2689584b961954</sys_id>
            <sys_mod_count>0</sys_mod_count>
            <sys_ui_formatter/>
            <sys_ui_section caption="Disease Surveillance" display_value="Disease Surveillance" name="x_cria_livestock_t_vaccinations_cvi" sys_domain="global" view="Default view">17d0c8b1dbaa17009b2689584b96197e</sys_ui_section>
            <sys_updated_by>cervin@criadvantage.com</sys_updated_by>
            <sys_updated_on>2018-06-07 16:42:59</sys_updated_on>
            <sys_user/>
            <type/>
        </sys_ui_element>
        <sys_ui_section action="DELETE">
            <caption>Disease Surveillance</caption>
            <header>false</header>
            <name>x_cria_livestock_t_vaccinations_cvi</name>
            <roles/>
            <sys_class_name>sys_ui_section</sys_class_name>
            <sys_created_by>dmorden@criadvantage.com</sys_created_by>
            <sys_created_on>2018-06-07 15:35:06</sys_created_on>
            <sys_domain>global</sys_domain>
            <sys_domain_path>/</sys_domain_path>
            <sys_id>17d0c8b1dbaa17009b2689584b96197e</sys_id>
            <sys_mod_count>0</sys_mod_count>
            <sys_name>Disease Surveillance</sys_name>
            <sys_overrides/>
            <sys_package display_value="Livestock Tracking" source="x_cria_livestock_t">7b1a2026dba09700df68f2b6ae96198c</sys_package>
            <sys_policy/>
            <sys_scope display_value="Livestock Tracking">7b1a2026dba09700df68f2b6ae96198c</sys_scope>
            <sys_update_name>sys_ui_section_17d0c8b1dbaa17009b2689584b96197e</sys_update_name>
            <sys_updated_by>dmorden@criadvantage.com</sys_updated_by>
            <sys_updated_on>2018-06-07 15:35:06</sys_updated_on>
            <sys_user/>
            <title>false</title>
            <view display_value="Default view" name="NULL">Default view</view>
            <view_name/>
        </sys_ui_section>
    </sys_ui_section>
<sys_update_version action="INSERT_OR_UPDATE">
        <action>DELETE</action>
        <application display_value="Livestock Tracking">7b1a2026dba09700df68f2b6ae96198c</application>
        <file_path/>
        <instance_id>e0ad35a6dbec57c0b2e05d00cf9619e7</instance_id>
        <instance_name>criadvantage</instance_name>
        <name>sys_ui_section_17d0c8b1dbaa17009b2689584b96197e</name>
        <payload><![CDATA[<?xml version="1.0" encoding="UTF-8"?><record_update>
    <sys_ui_section caption="Disease Surveillance" section_id="17d0c8b1dbaa17009b2689584b96197e" sys_domain="global" table="x_cria_livestock_t_vaccinations_cvi" version="3" view="">
        <sys_ui_element action="INSERT_OR_UPDATE">
            <element>cvi_brucellosis</element>
            <position>0</position>
            <sys_created_by>cervin@criadvantage.com</sys_created_by>
            <sys_created_on>2018-06-07 16:42:59</sys_created_on>
            <sys_id>bd609c7ddbaa17009b2689584b96194f</sys_id>
            <sys_mod_count>0</sys_mod_count>
            <sys_ui_formatter/>
            <sys_ui_section caption="Disease Surveillance" display_value="Disease Surveillance" name="x_cria_livestock_t_vaccinations_cvi" sys_domain="global" view="Default view">17d0c8b1dbaa17009b2689584b96197e</sys_ui_section>
            <sys_updated_by>cervin@criadvantage.com</sys_updated_by>
            <sys_updated_on>2018-06-07 16:42:59</sys_updated_on>
            <sys_user/>
            <type/>
        </sys_ui_element>
        <sys_ui_element action="INSERT_OR_UPDATE">
            <element>.split</element>
            <position>1</position>
            <sys_created_by>cervin@criadvantage.com</sys_created_by>
            <sys_created_on>2018-06-07 16:42:59</sys_created_on>
            <sys_id>35609c7ddbaa17009b2689584b961950</sys_id>
            <sys_mod_count>0</sys_mod_count>
            <sys_ui_formatter/>
            <sys_ui_section caption="Disease Surveillance" display_value="Disease Surveillance" name="x_cria_livestock_t_vaccinations_cvi" sys_domain="global" view="Default view">17d0c8b1dbaa17009b2689584b96197e</sys_ui_section>
            <sys_updated_by>cervin@criadvantage.com</sys_updated_by>
            <sys_updated_on>2018-06-07 16:42:59</sys_updated_on>
            <sys_user/>
            <type>.split</type>
        </sys_ui_element>
        <sys_ui_element action="INSERT_OR_UPDATE">
            <element>laboratory</element>
            <position>2</position>
            <sys_created_by>cervin@criadvantage.com</sys_created_by>
            <sys_created_on>2018-06-07 16:42:59</sys_created_on>
            <sys_id>b5609c7ddbaa17009b2689584b961950</sys_id>
            <sys_mod_count>0</sys_mod_count>
            <sys_ui_formatter/>
            <sys_ui_section caption="Disease Surveillance" display_value="Disease Surveillance" name="x_cria_livestock_t_vaccinations_cvi" sys_domain="global" view="Default view">17d0c8b1dbaa17009b2689584b96197e</sys_ui_section>
            <sys_updated_by>cervin@criadvantage.com</sys_updated_by>
            <sys_updated_on>2018-06-07 16:42:59</sys_updated_on>
            <sys_user/>
            <type/>
        </sys_ui_element>
        <sys_ui_element action="INSERT_OR_UPDATE">
            <element>date_bled</element>
            <position>3</position>
            <sys_created_by>cervin@criadvantage.com</sys_created_by>
            <sys_created_on>2018-06-07 16:42:59</sys_created_on>
            <sys_id>39609c7ddbaa17009b2689584b961950</sys_id>
            <sys_mod_count>0</sys_mod_count>
            <sys_ui_formatter/>
            <sys_ui_section caption="Disease Surveillance" display_value="Disease Surveillance" name="x_cria_livestock_t_vaccinations_cvi" sys_domain="global" view="Default view">17d0c8b1dbaa17009b2689584b96197e</sys_ui_section>
            <sys_updated_by>cervin@criadvantage.com</sys_updated_by>
            <sys_updated_on>2018-06-07 16:42:59</sys_updated_on>
            <sys_user/>
            <type/>
        </sys_ui_element>
        <sys_ui_element action="INSERT_OR_UPDATE">
            <element>number_of_test_eligible_cattle</element>
            <position>4</position>
            <sys_created_by>cervin@criadvantage.com</sys_created_by>
            <sys_created_on>2018-06-07 16:42:59</sys_created_on>
            <sys_id>b9609c7ddbaa17009b2689584b961950</sys_id>
            <sys_mod_count>0</sys_mod_count>
            <sys_ui_formatter/>
            <sys_ui_section caption="Disease Surveillance" display_value="Disease Surveillance" name="x_cria_livestock_t_vaccinations_cvi" sys_domain="global" view="Default view">17d0c8b1dbaa17009b2689584b96197e</sys_ui_section>
            <sys_updated_by>cervin@criadvantage.com</sys_updated_by>
            <sys_updated_on>2018-06-07 16:42:59</sys_updated_on>
            <sys_user/>
            <type/>
        </sys_ui_element>
        <sys_ui_element action="INSERT_OR_UPDATE">
            <element>number_of_brucellosis_negative_cattle</element>
            <position>5</position>
            <sys_created_by>cervin@criadvantage.com</sys_created_by>
            <sys_created_on>2018-06-07 16:42:59</sys_created_on>
            <sys_id>3d609c7ddbaa17009b2689584b961950</sys_id>
            <sys_mod_count>0</sys_mod_count>
            <sys_ui_formatter/>
            <sys_ui_section caption="Disease Surveillance" display_value="Disease Surveillance" name="x_cria_livestock_t_vaccinations_cvi" sys_domain="global" view="Default view">17d0c8b1dbaa17009b2689584b96197e</sys_ui_section>
            <sys_updated_by>cervin@criadvantage.com</sys_updated_by>
            <sys_updated_on>2018-06-07 16:42:59</sys_updated_on>
            <sys_user/>
            <type/>
        </sys_ui_element>
        <sys_ui_element action="INSERT_OR_UPDATE">
            <element>.end_split</element>
            <position>6</position>
            <sys_created_by>cervin@criadvantage.com</sys_created_by>
            <sys_created_on>2018-06-07 16:42:59</sys_created_on>
            <sys_id>bd609c7ddbaa17009b2689584b961950</sys_id>
            <sys_mod_count>0</sys_mod_count>
            <sys_ui_formatter/>
            <sys_ui_section caption="Disease Surveillance" display_value="Disease Surveillance" name="x_cria_livestock_t_vaccinations_cvi" sys_domain="global" view="Default view">17d0c8b1dbaa17009b2689584b96197e</sys_ui_section>
            <sys_updated_by>cervin@criadvantage.com</sys_updated_by>
            <sys_updated_on>2018-06-07 16:42:59</sys_updated_on>
            <sys_user/>
            <type>.end_split</type>
        </sys_ui_element>
        <sys_ui_element action="INSERT_OR_UPDATE">
            <element>.begin_split</element>
            <position>7</position>
            <sys_created_by>cervin@criadvantage.com</sys_created_by>
            <sys_created_on>2018-06-07 16:42:59</sys_created_on>
            <sys_id>31609c7ddbaa17009b2689584b961951</sys_id>
            <sys_mod_count>0</sys_mod_count>
            <sys_ui_formatter/>
            <sys_ui_section caption="Disease Surveillance" display_value="Disease Surveillance" name="x_cria_livestock_t_vaccinations_cvi" sys_domain="global" view="Default view">17d0c8b1dbaa17009b2689584b96197e</sys_ui_section>
            <sys_updated_by>cervin@criadvantage.com</sys_updated_by>
            <sys_updated_on>2018-06-07 16:42:59</sys_updated_on>
            <sys_user/>
            <type>.begin_split</type>
        </sys_ui_element>
        <sys_ui_element action="INSERT_OR_UPDATE">
            <element>cvi_trichomonisis</element>
            <position>8</position>
            <sys_created_by>cervin@criadvantage.com</sys_created_by>
            <sys_created_on>2018-06-07 16:42:59</sys_created_on>
            <sys_id>b1609c7ddbaa17009b2689584b961951</sys_id>
            <sys_mod_count>0</sys_mod_count>
            <sys_ui_formatter/>
            <sys_ui_section caption="Disease Surveillance" display_value="Disease Surveillance" name="x_cria_livestock_t_vaccinations_cvi" sys_domain="global" view="Default view">17d0c8b1dbaa17009b2689584b96197e</sys_ui_section>
            <sys_updated_by>cervin@criadvantage.com</sys_updated_by>
            <sys_updated_on>2018-06-07 16:42:59</sys_updated_on>
            <sys_user/>
            <type/>
        </sys_ui_element>
        <sys_ui_element action="INSERT_OR_UPDATE">
            <element>.split</element>
            <position>9</position>
            <sys_created_by>cervin@criadvantage.com</sys_created_by>
            <sys_created_on>2018-06-07 16:42:59</sys_created_on>
            <sys_id>35609c7ddbaa17009b2689584b961951</sys_id>
            <sys_mod_count>0</sys_mod_count>
            <sys_ui_formatter/>
            <sys_ui_section caption="Disease Surveillance" display_value="Disease Surveillance" name="x_cria_livestock_t_vaccinations_cvi" sys_domain="global" view="Default view">17d0c8b1dbaa17009b2689584b96197e</sys_ui_section>
            <sys_updated_by>cervin@criadvantage.com</sys_updated_by>
            <sys_updated_on>2018-06-07 16:42:59</sys_updated_on>
            <sys_user/>
            <type>.split</type>
        </sys_ui_element>
        <sys_ui_element action="INSERT_OR_UPDATE">
            <element>trich_laboratory</element>
            <position>10</position>
            <sys_created_by>cervin@criadvantage.com</sys_created_by>
            <sys_created_on>2018-06-07 16:42:59</sys_created_on>
            <sys_id>b5609c7ddbaa17009b2689584b961951</sys_id>
            <sys_mod_count>0</sys_mod_count>
            <sys_ui_formatter/>
            <sys_ui_section caption="Disease Surveillance" display_value="Disease Surveillance" name="x_cria_livestock_t_vaccinations_cvi" sys_domain="global" view="Default view">17d0c8b1dbaa17009b2689584b96197e</sys_ui_section>
            <sys_updated_by>cervin@criadvantage.com</sys_updated_by>
            <sys_updated_on>2018-06-07 16:42:59</sys_updated_on>
            <sys_user/>
            <type/>
        </sys_ui_element>
        <sys_ui_element action="INSERT_OR_UPDATE">
            <element>date_sample_collected</element>
            <position>11</position>
            <sys_created_by>cervin@criadvantage.com</sys_created_by>
            <sys_created_on>2018-06-07 16:42:59</sys_created_on>
            <sys_id>39609c7ddbaa17009b2689584b961951</sys_id>
            <sys_mod_count>0</sys_mod_count>
            <sys_ui_formatter/>
            <sys_ui_section caption="Disease Surveillance" display_value="Disease Surveillance" name="x_cria_livestock_t_vaccinations_cvi" sys_domain="global" view="Default view">17d0c8b1dbaa17009b2689584b96197e</sys_ui_section>
            <sys_updated_by>cervin@criadvantage.com</sys_updated_by>
            <sys_updated_on>2018-06-07 16:42:59</sys_updated_on>
            <sys_user/>
            <type/>
        </sys_ui_element>
        <sys_ui_element action="INSERT_OR_UPDATE">
            <element>accession_num</element>
            <position>12</position>
            <sys_created_by>cervin@criadvantage.com</sys_created_by>
            <sys_created_on>2018-06-07 16:42:59</sys_created_on>
            <sys_id>b9609c7ddbaa17009b2689584b961951</sys_id>
            <sys_mod_count>0</sys_mod_count>
            <sys_ui_formatter/>
            <sys_ui_section caption="Disease Surveillance" display_value="Disease Surveillance" name="x_cria_livestock_t_vaccinations_cvi" sys_domain="global" view="Default view">17d0c8b1dbaa17009b2689584b96197e</sys_ui_section>
            <sys_updated_by>cervin@criadvantage.com</sys_updated_by>
            <sys_updated_on>2018-06-07 16:42:59</sys_updated_on>
            <sys_user/>
            <type/>
        </sys_ui_element>
        <sys_ui_element action="INSERT_OR_UPDATE">
            <element>all_eligible_bulls_neg</element>
            <position>13</position>
            <sys_created_by>cervin@criadvantage.com</sys_created_by>
            <sys_created_on>2018-06-07 16:42:59</sys_created_on>
            <sys_id>3d609c7ddbaa17009b2689584b961951</sys_id>
            <sys_mod_count>0</sys_mod_count>
            <sys_ui_formatter/>
            <sys_ui_section caption="Disease Surveillance" display_value="Disease Surveillance" name="x_cria_livestock_t_vaccinations_cvi" sys_domain="global" view="Default view">17d0c8b1dbaa17009b2689584b96197e</sys_ui_section>
            <sys_updated_by>cervin@criadvantage.com</sys_updated_by>
            <sys_updated_on>2018-06-07 16:42:59</sys_updated_on>
            <sys_user/>
            <type/>
        </sys_ui_element>
        <sys_ui_element action="INSERT_OR_UPDATE">
            <element>.end_split</element>
            <position>14</position>
            <sys_created_by>cervin@criadvantage.com</sys_created_by>
            <sys_created_on>2018-06-07 16:42:59</sys_created_on>
            <sys_id>bd609c7ddbaa17009b2689584b961951</sys_id>
            <sys_mod_count>0</sys_mod_count>
            <sys_ui_formatter/>
            <sys_ui_section caption="Disease Surveillance" display_value="Disease Surveillance" name="x_cria_livestock_t_vaccinations_cvi" sys_domain="global" view="Default view">17d0c8b1dbaa17009b2689584b96197e</sys_ui_section>
            <sys_updated_by>cervin@criadvantage.com</sys_updated_by>
            <sys_updated_on>2018-06-07 16:42:59</sys_updated_on>
            <sys_user/>
            <type>.end_split</type>
        </sys_ui_element>
        <sys_ui_element action="INSERT_OR_UPDATE">
            <element>.begin_split</element>
            <position>15</position>
            <sys_created_by>cervin@criadvantage.com</sys_created_by>
            <sys_created_on>2018-06-07 16:42:59</sys_created_on>
            <sys_id>31609c7ddbaa17009b2689584b961952</sys_id>
            <sys_mod_count>0</sys_mod_count>
            <sys_ui_formatter/>
            <sys_ui_section caption="Disease Surveillance" display_value="Disease Surveillance" name="x_cria_livestock_t_vaccinations_cvi" sys_domain="global" view="Default view">17d0c8b1dbaa17009b2689584b96197e</sys_ui_section>
            <sys_updated_by>cervin@criadvantage.com</sys_updated_by>
            <sys_updated_on>2018-06-07 16:42:59</sys_updated_on>
            <sys_user/>
            <type>.begin_split</type>
        </sys_ui_element>
        <sys_ui_element action="INSERT_OR_UPDATE">
            <element>cvi_tuberculosis</element>
            <position>16</position>
            <sys_created_by>cervin@criadvantage.com</sys_created_by>
            <sys_created_on>2018-06-07 16:42:59</sys_created_on>
            <sys_id>b1609c7ddbaa17009b2689584b961952</sys_id>
            <sys_mod_count>0</sys_mod_count>
            <sys_ui_formatter/>
            <sys_ui_section caption="Disease Surveillance" display_value="Disease Surveillance" name="x_cria_livestock_t_vaccinations_cvi" sys_domain="global" view="Default view">17d0c8b1dbaa17009b2689584b96197e</sys_ui_section>
            <sys_updated_by>cervin@criadvantage.com</sys_updated_by>
            <sys_updated_on>2018-06-07 16:42:59</sys_updated_on>
            <sys_user/>
            <type/>
        </sys_ui_element>
        <sys_ui_element action="INSERT_OR_UPDATE">
            <element>.split</element>
            <position>17</position>
            <sys_created_by>cervin@criadvantage.com</sys_created_by>
            <sys_created_on>2018-06-07 16:42:59</sys_created_on>
            <sys_id>35609c7ddbaa17009b2689584b961952</sys_id>
            <sys_mod_count>0</sys_mod_count>
            <sys_ui_formatter/>
            <sys_ui_section caption="Disease Surveillance" display_value="Disease Surveillance" name="x_cria_livestock_t_vaccinations_cvi" sys_domain="global" view="Default view">17d0c8b1dbaa17009b2689584b96197e</sys_ui_section>
            <sys_updated_by>cervin@criadvantage.com</sys_updated_by>
            <sys_updated_on>2018-06-07 16:42:59</sys_updated_on>
            <sys_user/>
            <type>.split</type>
        </sys_ui_element>
        <sys_ui_element action="INSERT_OR_UPDATE">
            <element>all_animals_neg</element>
            <position>18</position>
            <sys_created_by>cervin@criadvantage.com</sys_created_by>
            <sys_created_on>2018-06-07 16:42:59</sys_created_on>
            <sys_id>b5609c7ddbaa17009b2689584b961952</sys_id>
            <sys_mod_count>0</sys_mod_count>
            <sys_ui_formatter/>
            <sys_ui_section caption="Disease Surveillance" display_value="Disease Surveillance" name="x_cria_livestock_t_vaccinations_cvi" sys_domain="global" view="Default view">17d0c8b1dbaa17009b2689584b96197e</sys_ui_section>
            <sys_updated_by>cervin@criadvantage.com</sys_updated_by>
            <sys_updated_on>2018-06-07 16:42:59</sys_updated_on>
            <sys_user/>
            <type/>
        </sys_ui_element>
        <sys_ui_element action="INSERT_OR_UPDATE">
            <element>tub_date</element>
            <position>19</position>
            <sys_created_by>cervin@criadvantage.com</sys_created_by>
            <sys_created_on>2018-06-07 16:42:59</sys_created_on>
            <sys_id>39609c7ddbaa17009b2689584b961952</sys_id>
            <sys_mod_count>0</sys_mod_count>
            <sys_ui_formatter/>
            <sys_ui_section caption="Disease Surveillance" display_value="Disease Surveillance" name="x_cria_livestock_t_vaccinations_cvi" sys_domain="global" view="Default view">17d0c8b1dbaa17009b2689584b96197e</sys_ui_section>
            <sys_updated_by>cervin@criadvantage.com</sys_updated_by>
            <sys_updated_on>2018-06-07 16:42:59</sys_updated_on>
            <sys_user/>
            <type/>
        </sys_ui_element>
        <sys_ui_element action="INSERT_OR_UPDATE">
            <element>.end_split</element>
            <position>20</position>
            <sys_created_by>cervin@criadvantage.com</sys_created_by>
            <sys_created_on>2018-06-07 16:42:59</sys_created_on>
            <sys_id>b9609c7ddbaa17009b2689584b961952</sys_id>
            <sys_mod_count>0</sys_mod_count>
            <sys_ui_formatter/>
            <sys_ui_section caption="Disease Surveillance" display_value="Disease Surveillance" name="x_cria_livestock_t_vaccinations_cvi" sys_domain="global" view="Default view">17d0c8b1dbaa17009b2689584b96197e</sys_ui_section>
            <sys_updated_by>cervin@criadvantage.com</sys_updated_by>
            <sys_updated_on>2018-06-07 16:42:59</sys_updated_on>
            <sys_user/>
            <type>.end_split</type>
        </sys_ui_element>
        <sys_ui_element action="INSERT_OR_UPDATE">
            <element>.begin_split</element>
            <position>21</position>
            <sys_created_by>cervin@criadvantage.com</sys_created_by>
            <sys_created_on>2018-06-07 16:42:59</sys_created_on>
            <sys_id>3d609c7ddbaa17009b2689584b961952</sys_id>
            <sys_mod_count>0</sys_mod_count>
            <sys_ui_formatter/>
            <sys_ui_section caption="Disease Surveillance" display_value="Disease Surveillance" name="x_cria_livestock_t_vaccinations_cvi" sys_domain="global" view="Default view">17d0c8b1dbaa17009b2689584b96197e</sys_ui_section>
            <sys_updated_by>cervin@criadvantage.com</sys_updated_by>
            <sys_updated_on>2018-06-07 16:42:59</sys_updated_on>
            <sys_user/>
            <type>.begin_split</type>
        </sys_ui_element>
        <sys_ui_element action="INSERT_OR_UPDATE">
            <element>cvi_equine_infectious_anemia</element>
            <position>22</position>
            <sys_created_by>cervin@criadvantage.com</sys_created_by>
            <sys_created_on>2018-06-07 16:42:59</sys_created_on>
            <sys_id>bd609c7ddbaa17009b2689584b961952</sys_id>
            <sys_mod_count>0</sys_mod_count>
            <sys_ui_formatter/>
            <sys_ui_section caption="Disease Surveillance" display_value="Disease Surveillance" name="x_cria_livestock_t_vaccinations_cvi" sys_domain="global" view="Default view">17d0c8b1dbaa17009b2689584b96197e</sys_ui_section>
            <sys_updated_by>cervin@criadvantage.com</sys_updated_by>
            <sys_updated_on>2018-06-07 16:42:59</sys_updated_on>
            <sys_user/>
            <type/>
        </sys_ui_element>
        <sys_ui_element action="INSERT_OR_UPDATE">
            <element>.split</element>
            <position>23</position>
            <sys_created_by>cervin@criadvantage.com</sys_created_by>
            <sys_created_on>2018-06-07 16:42:59</sys_created_on>
            <sys_id>31609c7ddbaa17009b2689584b961953</sys_id>
            <sys_mod_count>0</sys_mod_count>
            <sys_ui_formatter/>
            <sys_ui_section caption="Disease Surveillance" display_value="Disease Surveillance" name="x_cria_livestock_t_vaccinations_cvi" sys_domain="global" view="Default view">17d0c8b1dbaa17009b2689584b96197e</sys_ui_section>
            <sys_updated_by>cervin@criadvantage.com</sys_updated_by>
            <sys_updated_on>2018-06-07 16:42:59</sys_updated_on>
            <sys_user/>
            <type>.split</type>
        </sys_ui_element>
        <sys_ui_element action="INSERT_OR_UPDATE">
            <element>eia_laboratory</element>
            <position>24</position>
            <sys_created_by>cervin@criadvantage.com</sys_created_by>
            <sys_created_on>2018-06-07 16:42:59</sys_created_on>
            <sys_id>b1609c7ddbaa17009b2689584b961953</sys_id>
            <sys_mod_count>0</sys_mod_count>
            <sys_ui_formatter/>
            <sys_ui_section caption="Disease Surveillance" display_value="Disease Surveillance" name="x_cria_livestock_t_vaccinations_cvi" sys_domain="global" view="Default view">17d0c8b1dbaa17009b2689584b96197e</sys_ui_section>
            <sys_updated_by>cervin@criadvantage.com</sys_updated_by>
            <sys_updated_on>2018-06-07 16:42:59</sys_updated_on>
            <sys_user/>
            <type/>
        </sys_ui_element>
        <sys_ui_element action="INSERT_OR_UPDATE">
            <element>eia_accession</element>
            <position>25</position>
            <sys_created_by>cervin@criadvantage.com</sys_created_by>
            <sys_created_on>2018-06-07 16:42:59</sys_created_on>
            <sys_id>35609c7ddbaa17009b2689584b961953</sys_id>
            <sys_mod_count>0</sys_mod_count>
            <sys_ui_formatter/>
            <sys_ui_section caption="Disease Surveillance" display_value="Disease Surveillance" name="x_cria_livestock_t_vaccinations_cvi" sys_domain="global" view="Default view">17d0c8b1dbaa17009b2689584b96197e</sys_ui_section>
            <sys_updated_by>cervin@criadvantage.com</sys_updated_by>
            <sys_updated_on>2018-06-07 16:42:59</sys_updated_on>
            <sys_user/>
            <type/>
        </sys_ui_element>
        <sys_ui_element action="INSERT_OR_UPDATE">
            <element>date_of_coggins</element>
            <position>26</position>
            <sys_created_by>cervin@criadvantage.com</sys_created_by>
            <sys_created_on>2018-06-07 16:42:59</sys_created_on>
            <sys_id>b5609c7ddbaa17009b2689584b961953</sys_id>
            <sys_mod_count>0</sys_mod_count>
            <sys_ui_formatter/>
            <sys_ui_section caption="Disease Surveillance" display_value="Disease Surveillance" name="x_cria_livestock_t_vaccinations_cvi" sys_domain="global" view="Default view">17d0c8b1dbaa17009b2689584b96197e</sys_ui_section>
            <sys_updated_by>cervin@criadvantage.com</sys_updated_by>
            <sys_updated_on>2018-06-07 16:42:59</sys_updated_on>
            <sys_user/>
            <type/>
        </sys_ui_element>
        <sys_ui_element action="INSERT_OR_UPDATE">
            <element>.end_split</element>
            <position>27</position>
            <sys_created_by>cervin@criadvantage.com</sys_created_by>
            <sys_created_on>2018-06-07 16:42:59</sys_created_on>
            <sys_id>39609c7ddbaa17009b2689584b961953</sys_id>
            <sys_mod_count>0</sys_mod_count>
            <sys_ui_formatter/>
            <sys_ui_section caption="Disease Surveillance" display_value="Disease Surveillance" name="x_cria_livestock_t_vaccinations_cvi" sys_domain="global" view="Default view">17d0c8b1dbaa17009b2689584b96197e</sys_ui_section>
            <sys_updated_by>cervin@criadvantage.com</sys_updated_by>
            <sys_updated_on>2018-06-07 16:42:59</sys_updated_on>
            <sys_user/>
            <type>.end_split</type>
        </sys_ui_element>
        <sys_ui_element action="INSERT_OR_UPDATE">
            <element>.begin_split</element>
            <position>28</position>
            <sys_created_by>cervin@criadvantage.com</sys_created_by>
            <sys_created_on>2018-06-07 16:42:59</sys_created_on>
            <sys_id>b9609c7ddbaa17009b2689584b961953</sys_id>
            <sys_mod_count>0</sys_mod_count>
            <sys_ui_formatter/>
            <sys_ui_section caption="Disease Surveillance" display_value="Disease Surveillance" name="x_cria_livestock_t_vaccinations_cvi" sys_domain="global" view="Default view">17d0c8b1dbaa17009b2689584b96197e</sys_ui_section>
            <sys_updated_by>cervin@criadvantage.com</sys_updated_by>
            <sys_updated_on>2018-06-07 16:42:59</sys_updated_on>
            <sys_user/>
            <type>.begin_split</type>
        </sys_ui_element>
        <sys_ui_element action="INSERT_OR_UPDATE">
            <element>cvi_other</element>
            <position>29</position>
            <sys_created_by>cervin@criadvantage.com</sys_created_by>
            <sys_created_on>2018-06-07 16:42:59</sys_created_on>
            <sys_id>3d609c7ddbaa17009b2689584b961953</sys_id>
            <sys_mod_count>0</sys_mod_count>
            <sys_ui_formatter/>
            <sys_ui_section caption="Disease Surveillance" display_value="Disease Surveillance" name="x_cria_livestock_t_vaccinations_cvi" sys_domain="global" view="Default view">17d0c8b1dbaa17009b2689584b96197e</sys_ui_section>
            <sys_updated_by>cervin@criadvantage.com</sys_updated_by>
            <sys_updated_on>2018-06-07 16:42:59</sys_updated_on>
            <sys_user/>
            <type/>
        </sys_ui_element>
        <sys_ui_element action="INSERT_OR_UPDATE">
            <element>.split</element>
            <position>30</position>
            <sys_created_by>cervin@criadvantage.com</sys_created_by>
            <sys_created_on>2018-06-07 16:42:59</sys_created_on>
            <sys_id>bd609c7ddbaa17009b2689584b961953</sys_id>
            <sys_mod_count>0</sys_mod_count>
            <sys_ui_formatter/>
            <sys_ui_section caption="Disease Surveillance" display_value="Disease Surveillance" name="x_cria_livestock_t_vaccinations_cvi" sys_domain="global" view="Default view">17d0c8b1dbaa17009b2689584b96197e</sys_ui_section>
            <sys_updated_by>cervin@criadvantage.com</sys_updated_by>
            <sys_updated_on>2018-06-07 16:42:59</sys_updated_on>
            <sys_user/>
            <type>.split</type>
        </sys_ui_element>
        <sys_ui_element action="INSERT_OR_UPDATE">
            <element>other_test</element>
            <position>31</position>
            <sys_created_by>cervin@criadvantage.com</sys_created_by>
            <sys_created_on>2018-06-07 16:42:59</sys_created_on>
            <sys_id>31609c7ddbaa17009b2689584b961954</sys_id>
            <sys_mod_count>0</sys_mod_count>
            <sys_ui_formatter/>
            <sys_ui_section caption="Disease Surveillance" display_value="Disease Surveillance" name="x_cria_livestock_t_vaccinations_cvi" sys_domain="global" view="Default view">17d0c8b1dbaa17009b2689584b96197e</sys_ui_section>
            <sys_updated_by>cervin@criadvantage.com</sys_updated_by>
            <sys_updated_on>2018-06-07 16:42:59</sys_updated_on>
            <sys_user/>
            <type/>
        </sys_ui_element>
        <sys_ui_element action="INSERT_OR_UPDATE">
            <element>other_results</element>
            <position>32</position>
            <sys_created_by>cervin@criadvantage.com</sys_created_by>
            <sys_created_on>2018-06-07 16:42:59</sys_created_on>
            <sys_id>b1609c7ddbaa17009b2689584b961954</sys_id>
            <sys_mod_count>0</sys_mod_count>
            <sys_ui_formatter/>
            <sys_ui_section caption="Disease Surveillance" display_value="Disease Surveillance" name="x_cria_livestock_t_vaccinations_cvi" sys_domain="global" view="Default view">17d0c8b1dbaa17009b2689584b96197e</sys_ui_section>
            <sys_updated_by>cervin@criadvantage.com</sys_updated_by>
            <sys_updated_on>2018-06-07 16:42:59</sys_updated_on>
            <sys_user/>
            <type/>
        </sys_ui_element>
        <sys_ui_element action="INSERT_OR_UPDATE">
            <element>other_lab</element>
            <position>33</position>
            <sys_created_by>cervin@criadvantage.com</sys_created_by>
            <sys_created_on>2018-06-07 16:42:59</sys_created_on>
            <sys_id>35609c7ddbaa17009b2689584b961954</sys_id>
            <sys_mod_count>0</sys_mod_count>
            <sys_ui_formatter/>
            <sys_ui_section caption="Disease Surveillance" display_value="Disease Surveillance" name="x_cria_livestock_t_vaccinations_cvi" sys_domain="global" view="Default view">17d0c8b1dbaa17009b2689584b96197e</sys_ui_section>
            <sys_updated_by>cervin@criadvantage.com</sys_updated_by>
            <sys_updated_on>2018-06-07 16:42:59</sys_updated_on>
            <sys_user/>
            <type/>
        </sys_ui_element>
        <sys_ui_section action="INSERT_OR_UPDATE">
            <caption>Disease Surveillance</caption>
            <header>false</header>
            <name>x_cria_livestock_t_vaccinations_cvi</name>
            <roles/>
            <sys_class_name>sys_ui_section</sys_class_name>
            <sys_created_by>dmorden@criadvantage.com</sys_created_by>
            <sys_created_on>2018-06-07 15:35:06</sys_created_on>
            <sys_domain>global</sys_domain>
            <sys_domain_path>/</sys_domain_path>
            <sys_id>17d0c8b1dbaa17009b2689584b96197e</sys_id>
            <sys_mod_count>0</sys_mod_count>
            <sys_name>Disease Surveillance</sys_name>
            <sys_overrides/>
            <sys_package display_value="Livestock Tracking" source="x_cria_livestock_t">7b1a2026dba09700df68f2b6ae96198c</sys_package>
            <sys_policy/>
            <sys_scope display_value="Livestock Tracking">7b1a2026dba09700df68f2b6ae96198c</sys_scope>
            <sys_update_name>sys_ui_section_17d0c8b1dbaa17009b2689584b96197e</sys_update_name>
            <sys_updated_by>dmorden@criadvantage.com</sys_updated_by>
            <sys_updated_on>2018-06-07 15:35:06</sys_updated_on>
            <sys_user/>
            <title>false</title>
            <view display_value="Default view" name="NULL">Default view</view>
            <view_name/>
        </sys_ui_section>
    </sys_ui_section>
</record_update>]]></payload>
        <payload_hash>1230350584</payload_hash>
        <record_name>CVI / Health Certificate</record_name>
        <reverted_from/>
        <source>a09d1916db7a570066015d104b9619c5</source>
        <source_table>sys_upgrade_history</source_table>
        <state>previous</state>
        <sys_created_by>system</sys_created_by>
        <sys_created_on>2018-06-21 21:55:00</sys_created_on>
        <sys_id>7c1e55d6db7a570066015d104b9619f2</sys_id>
        <sys_mod_count>0</sys_mod_count>
        <sys_recorded_at>1642457f2ee0000001</sys_recorded_at>
        <sys_updated_by>system</sys_updated_by>
        <sys_updated_on>2018-06-21 21:55:00</sys_updated_on>
        <type>Form Layout</type>
        <update_guid>b81e55d6fd7a5700b353844fe55e90f2</update_guid>
        <update_guid_history>b81e55d6fd7a5700b353844fe55e90f2:0,2d63641e86b65700298a206c5c99d7b6:1844068419,39609c7d35aa1700daf2360a8301c059:379767844,772544b5c8aa1700461706735f02a1fc:909140598,efd04cb11baa1700ef10dba318eb2a5d:-599388657</update_guid_history>
    </sys_update_version>
    <sys_metadata_delete action="INSERT_OR_UPDATE">
        <sys_audit_delete/>
        <sys_class_name>sys_metadata_delete</sys_class_name>
        <sys_created_by>thigley@criadvantage.com</sys_created_by>
        <sys_created_on>2019-07-02 16:12:44</sys_created_on>
        <sys_db_object display_value="" name="sys_ui_section">sys_ui_section</sys_db_object>
        <sys_id>68456ab71cd54c0a83155412824e6304</sys_id>
        <sys_metadata>17d0c8b1dbaa17009b2689584b96197e</sys_metadata>
        <sys_mod_count>0</sys_mod_count>
        <sys_name>Disease Surveillance</sys_name>
        <sys_package display_value="Livestock Tracking" source="x_cria_livestock_t">7b1a2026dba09700df68f2b6ae96198c</sys_package>
        <sys_parent display_value="Export CVI">5655c4f0db421700c64e5eea4b961998</sys_parent>
        <sys_policy/>
        <sys_scope display_value="Livestock Tracking">7b1a2026dba09700df68f2b6ae96198c</sys_scope>
        <sys_scope_delete display_value="">0a9ea1241d954d4780e5f90c82e9f819</sys_scope_delete>
        <sys_update_name>sys_ui_section_17d0c8b1dbaa17009b2689584b96197e</sys_update_name>
        <sys_update_version display_value="sys_ui_section_17d0c8b1dbaa17009b2689584b96197e">7c1e55d6db7a570066015d104b9619f2</sys_update_version>
        <sys_updated_by>thigley@criadvantage.com</sys_updated_by>
        <sys_updated_on>2019-07-02 16:12:44</sys_updated_on>
    </sys_metadata_delete>
</record_update>
